CHANGES.txt
README.txt
ZopePublicLicense.txt
bootstrap.py
buildout.cfg
setup.py
src/zope/__init__.py
src/zope.wfmc.egg-info/PKG-INFO
src/zope.wfmc.egg-info/SOURCES.txt
src/zope.wfmc.egg-info/dependency_links.txt
src/zope.wfmc.egg-info/namespace_packages.txt
src/zope.wfmc.egg-info/not-zip-safe
src/zope.wfmc.egg-info/requires.txt
src/zope.wfmc.egg-info/top_level.txt
src/zope/wfmc/README.txt
src/zope/wfmc/__init__.py
src/zope/wfmc/attributeintegration.py
src/zope/wfmc/interfaces.py
src/zope/wfmc/process.py
src/zope/wfmc/publication.xpdl
src/zope/wfmc/tests.py
src/zope/wfmc/xpdl.py
src/zope/wfmc/xpdl.txt
src/zope/wfmc/adapter/__init__.py
src/zope/wfmc/adapter/integration.py
src/zope/wfmc/adapter/integration.txt
src/zope/wfmc/adapter/tests.py