Metadata-Version: 1.0
Name: zope.wfmc
Version: 3.5.0
Summary: Workflow-Management Coalition Workflow Engine
Home-page: http://cheeseshop.python.org/pypi/zope.wfmc
Author: Zope Corporation and Contributors
Author-email: zope3-dev@zope.org
License: ZPL 2.1
Keywords: zope3 wfmc xpdl workflow engine
Platform: UNKNOWN
Classifier: Development Status :: 5 - Production/Stable
Classifier: Environment :: Web Environment
Classifier: Intended Audience :: Developers
Classifier: License :: OSI Approved :: Zope Public License
Classifier: Programming Language :: Python
Classifier: Natural Language :: English
Classifier: Operating System :: OS Independent
Classifier: Topic :: Internet :: WWW/HTTP
Classifier: Framework :: Zope3
